WXApi/WXError.py
WXApi/WXMenu.py
WXApi/WXUtils.py
WXApi/__init__.py
WXApi/event.py
WXApi/request.py
pyweipi-1.0.7.dist-info/METADATA
pyweipi-1.0.7.dist-info/WHEEL
pyweipi-1.0.7.dist-info/top_level.txt
pyweipi-1.0.7.dist-info/RECORD
