Metadata-Version: 2.1
Name: pyweipi
Version: 1.0.7
Summary: Python 2.x 3.x api for Weixin or Weibo platform
Home-page: https://github.com/KEDYY/pyweipi
Author: Yifei0727
Author-email: Yifei0727@users.noreply.github.com
License: MIT
Keywords: weixin,weibo,api
Platform: any
Classifier: Development Status :: 3 - Alpha
Classifier: Intended Audience :: Developers
Classifier: Topic :: Software Development :: Libraries :: Python Modules
Classifier: License :: OSI Approved :: MIT License
Classifier: Programming Language :: Python :: 2
Classifier: Programming Language :: Python :: 2.6
Classifier: Programming Language :: Python :: 2.7
Classifier: Programming Language :: Python :: 3
Classifier: Programming Language :: Python :: 3.3
Classifier: Programming Language :: Python :: 3.4
Classifier: Programming Language :: Python :: 3.5
Classifier: Programming Language :: Python :: 3.6
Classifier: Programming Language :: Python :: 3.7
Requires-Dist: requests (>=2.0)
